README.md
setup.cfg
setup.py
ohapi/__init__.py
ohapi/api.py
ohapi/command_line.py
ohapi/projects.py
ohapi/public.py
ohapi/utils_fs.py
open_humans_api.egg-info/PKG-INFO
open_humans_api.egg-info/SOURCES.txt
open_humans_api.egg-info/dependency_links.txt
open_humans_api.egg-info/entry_points.txt
open_humans_api.egg-info/requires.txt
open_humans_api.egg-info/top_level.txt