Metadata-Version: 2.1
Name: open-humans-api
Version: 0.2.8
Summary: Tools for working with Open Humans APIs
Home-page: https://github.com/OpenHumans/open-humans-api
Author: Mad Price Ball
Author-email: support@openhumans.org
License: MIT
Keywords: open-humans
Platform: UNKNOWN
Classifier: Environment :: Console
Classifier: Development Status :: 3 - Alpha
Classifier: Intended Audience :: Developers
Classifier: Intended Audience :: End Users/Desktop
Classifier: Intended Audience :: Information Technology
Classifier: Intended Audience :: System Administrators
Classifier: License :: OSI Approved :: BSD License
Classifier: Operating System :: POSIX
Classifier: Operating System :: MacOS :: MacOS X
Classifier: Operating System :: Microsoft :: Windows
Classifier: Programming Language :: Python
Classifier: Topic :: Utilities
